synoku/__init__.py
synoku-0.1.0.dist-info/licenses/LICENSE
synoku-0.1.0.dist-info/METADATA
synoku-0.1.0.dist-info/WHEEL
synoku-0.1.0.dist-info/top_level.txt
synoku-0.1.0.dist-info/RECORD
